Metadata-Version: 2.1
Name: easyi
Version: 0.0.1
Summary: Use TCP or UDP
Home-page: https://github.com/pyconjinji/easyi
Author: 王崇林
Author-email: colins.wang@outlook.com
Classifier: Programming Language :: Python :: 3
Classifier: License :: OSI Approved :: MIT License
Classifier: Operating System :: OS Independent
Requires-Python: >=3.8
License-File: LICENSE.txt
